dotstruct/__init__.py
dotstruct/queue.py
dotstruct/stack.py
dotgen-0.2.0.dist-info/METADATA
dotgen-0.2.0.dist-info/WHEEL
dotgen-0.2.0.dist-info/top_level.txt
dotgen-0.2.0.dist-info/RECORD
