Metadata-Version: 2.1
Name: dotgen
Version: 0.2.0
Summary: Created Python library
Home-page: UNKNOWN
Author: Claudio Lau
License: MIT
Platform: UNKNOWN
